allied_vision_api/__init__.py
allied_vision_api/camera_api.py
allied_vision_api/camera_device.py
allied_vision_api/camera_feature_command.py
allied_vision_api/controller.py
allied_vision_api/example/__init__.py
allied_vision_api/example/camera_api_example.py
allied_vision_api/exception.py
allied_vision_api-0.1.12.dist-info/METADATA
allied_vision_api-0.1.12.dist-info/WHEEL
allied_vision_api-0.1.12.dist-info/RECORD
